ft_package/__init__.py
ft_package/count_in_list.py
ft_package_chanwjeo-0.0.1.dist-info/LICENSE
ft_package_chanwjeo-0.0.1.dist-info/METADATA
ft_package_chanwjeo-0.0.1.dist-info/WHEEL
ft_package_chanwjeo-0.0.1.dist-info/top_level.txt
ft_package_chanwjeo-0.0.1.dist-info/RECORD
