Metadata-Version: 2.1
Name: ft-package-chanwjeo
Version: 0.0.1
Summary: A sample test package
Home-page: https://github.com/chanwoong1
Author: chanwjeo
Author-email: chanwjeo@student.42seoul.kr
License: MIT
Classifier: Programming Language :: Python :: 3
Classifier: License :: OSI Approved :: MIT License
Classifier: Operating System :: OS Independent
License-File: LICENSE
